decaf/__init__.py
decaf/config/__init__.py
decaf/filters/__init__.py
decaf/filters/filters.py
decaf/index/__init__.py
decaf/index/index.py
decaf/index/literal.py
decaf/index/structure.py
decaf/index/views.py
decaffinate-0.1.dist-info/licenses/LICENSE
scripts/analyze/cooccurence.py
scripts/analyze/overlap.py
scripts/export/all.py
scripts/export/filtered.py
scripts/import/ud.py
decaffinate-0.1.dist-info/METADATA
decaffinate-0.1.dist-info/WHEEL
decaffinate-0.1.dist-info/top_level.txt
decaffinate-0.1.dist-info/RECORD
