Metadata-Version: 2.4
Name: decaffinate
Version: 0.1
Summary: A Dynamically Extensible Corpus Analysis Framework
Author-email: Max Müller-Eberstein <decaf@personads.me>
License-Expression: MIT
Project-URL: Homepage, https://mxij.me/x/decaf
Classifier: Programming Language :: Python :: 3
Classifier: Operating System :: OS Independent
Requires-Python: >=3.6
License-File: LICENSE
Provides-Extra: full
Requires-Dist: conllu>=6.0.0; extra == "full"
Requires-Dist: matplotlib>=3.9.0; extra == "full"
Requires-Dist: notebook>=7.3.0; extra == "full"
Requires-Dist: numpy>=2.0.0; extra == "full"
Requires-Dist: pandas>=2.2.0; extra == "full"
Requires-Dist: scipy>=1.13.0; extra == "full"
Requires-Dist: sqlparse>=0.5.0; extra == "full"
Dynamic: license-file
